LICENSE
MANIFEST.in
README.rst
setup.cfg
setup.py
tuna_wrap/__init__.py
tuna_wrap/wrap.py
tuna_wrap.egg-info/PKG-INFO
tuna_wrap.egg-info/SOURCES.txt
tuna_wrap.egg-info/dependency_links.txt
tuna_wrap.egg-info/entry_points.txt
tuna_wrap.egg-info/top_level.txt