Metadata-Version: 2.1
Name: tuna-wrap
Version: 0.1.3
Summary: Wraps Nautilus scripts for use in Thunar file manager
Home-page: UNKNOWN
Author: Andreas Fritz
Author-email: py.project@quantentunnel.de
License: UNKNOWN
Download-URL: https://pypi.python.org/pypi/tuna-wrap
Keywords: Thunar Nautilus script wrapper
Platform: UNKNOWN
Classifier: Development Status :: 4 - Beta
Classifier: License :: OSI Approved :: MIT License
Classifier: Operating System :: Unix
Classifier: Programming Language :: Python :: 3
Classifier: Environment :: Console
Classifier: Natural Language :: English
Classifier: Intended Audience :: End Users/Desktop
Classifier: Topic :: Desktop Environment
Classifier: Topic :: Desktop Environment :: File Managers
Classifier: Topic :: Desktop Environment :: Gnome
License-File: LICENSE
